> ⚠️ **Under Development:** This chapter is currently being written and compiled. Code snippets, explanations, and under-the-hood deep dives are subject to active updates.

© 2026 David Vael | Licensed under CC-BY 4.0
### The `if` Statement in Python
The `if` statement is one of the most fundamental building blocks of programming in Python. It allows your program to make decisions and execute specific code blocks only when certain conditions are met a concept known as **conditional execution** or **control flow**. Without conditional statements, software would be entirely linear and rigid, running the exact same way every time without any ability to respond to varying inputs or states.

### 📋 Basic Syntax
The foundational structural layout of an `if` statement relies entirely on Python's unique, whitespace-driven block-scoping rules:
```python
if condition:
    # Code block to execute
    # This runs only if the condition evaluates to True or Truthy
```

### Key Components:
- **The if Keyword:** Initiates the conditional evaluation check sequence inside the execution scope.
- **The Condition:** An expression that is evaluated down to a Boolean value (`True` or `False`). If the target expression yields a non-Boolean object (e.g., a list, string, or number), Python automatically evaluates its implicit truthiness or falsiness using its internal `PyObject_IsTrue()` C-level logic slots.
- **The Colon (`:`):** A mandatory character at the termination of the conditional clause line. It serves as a structural token signaling to the compiler that an indented code block follows immediately.
- **Indentation:** The lines of code intended to execute within the true branch path must be uniformly indented (the universal Python standard is 4 spaces). Unlike languages like C++, Java, or JavaScript that utilize explicit curly braces `{}` to isolate local scopes, Python enforces structural semantic layout directly via whitespace constraints.

### ⚙️ How It Works
When the CPython runtime engine encounters an `if` statement, it executes a clean, three step evaluation and branching routine.
```text
[ Evaluate Condition Expression ]
                       |
             Is it Truthy / True?
                    /     \
                (Yes)     (No)
                 /           \
     [ Run Indented Block ]   |
                 \           /
       [ Continue Program Execution ]
```
1. **Evaluate the Condition Expression:** The virtual machine engine processes the expression to determine whether it safely maps down to a `True` or `False` state.
2. **Execute Conditionally:**
    - **The True Path:** If the condition evaluates to `True`, the execution pointer enters the indented code block space and runs the statements inside sequentially.
    - **The False Path:** If the condition evaluates to `False`, the virtual machine alters its internal instruction registry pointer to hop over the indented code block entirely.
3. **Resume Linear Execution:** Once the conditional block has either successfully finished running or been bypassed by the engine, Python resumes executing the remaining unindented code lines sequentially down the file.

### 📋 Code Implementation Examples

## Example 1: Basic Condition with Comparison
```python
age = 18
if age >= 18:
    print("You are eligible to vote")
```
**Step-By-Step Breakdown:**
1. **Variable Assignment:** `age = 18` creates the identifier reference name `age` and binds it to a `PyLongObject` integer value of `18` in the local namespace.
2. **Condition Check:** `age >= 18` invokes the greater-than-or-equal-to comparison operator to evaluate the value bound to `age` against the literal `18`.
3. **Evaluation:** Since $18 \ge 18$ is mathematically true, the expression yields a pointer reference to the global Boolean singleton `True`.
4. **Execution:** The condition passes, triggering the indented block. The `print()` function executes and displays: `You are eligible to vote`.

## What if `age` was 17?
```python
age = 17
if age >= 18:
print("You are eligible to vote")
```
Now, the comparison expression evaluates $17 \ge 18$, which yields `False`. Because the condition fails, the virtual machine shifts its internal instruction registry pointer to hop directly over the indented print block. The program simply moves on to the next unindented line, and nothing is printed to `stdout`.

### 🧠 What's happening behind the scenes:
Let’s lift up the hood and look at the exact CPython bytecode generated for this basic `if` statement block. When Python compiles this script, it uses conditional jump instructions to handle the execution flow routing.

If we pass this code through Python’s internal `dis` (disassembler) module, the bytecode layout resolves like this:

```text
1           0 LOAD_NAME                0 (age)
              2 LOAD_CONST               0 (18)
              4 COMPARE_OP              74 (>=)
             10 POP_JUMP_IF_FALSE        6 (to 24)

2            12 LOAD_NAME                1 (print)
             14 LOAD_CONST               1 ('You are eligible to vote')
             16 CALL                     1
             22 POP_TOP
        >>   24 LOAD_CONST               2 (None)
             26 RETURN_VALUE
```

**The Evaluation Flow Control Steps:**
1. **`LOAD_NAME` & `LOAD_CONST`:** CPython pushes the value pointer stored in the variable `age` onto the evaluation stack, followed quickly by the constant literal value `18`.
2. **COMPARE_OP:** The virtual machine pops both values off the stack, executes the binary comparison (`>=`) at the C layer, and pushes the resulting boolean singleton (`True` or `False`) right back onto the head of the evaluation stack.
3. **`POP_JUMP_IF_FALSE`:** This is where the core magic of control flow routing happens. This instruction pops the Boolean result off the top of the stack and inspects its state:
    - **The `True` Path:** If the value is `True`, the instruction does nothing, and the virtual machine naturally slips down to the very next sequence line of bytecode (`LOAD_NAME` for the print function at offset 12).
    - **The `False` Path:** If the value is `False`, the instruction updates the VM's internal instruction pointer registry and completely jumps the execution track down to offset `24` (`LOAD_CONST None`). By forcing a branch jump directly to offset 24, it entirely skips the sequential instructions responsible for loading, setting up, and invoking the `CALL` stack for the `print()` function!
   

### Example 2: Using a Boolean Variable
```python
is_logged_in = True
if is_logged_in:
    print("Welcome back!")
```

## Step-By-Step Breakdown:
1. **Boolean Evaluation:** The identifier name `is_logged_in` is directly bound to the global Boolean singleton `True`. Because it is already a Boolean object, no evaluation modifier or comparison operator is required.
2. **Direct Evaluation:** Writing `if is_logged_in:` is functionally identical to writing `if is_logged_in == True:`, but the shorter form bypasses raw comparison overhead and is the highly preferred, idiomatic Pythonic approach.
3. **Result:** Since the variable directly holds a true value, the condition evaluates successfully and prints: `Welcome back!`.

## Alternative: Checking for `False` states with Logical Inversion
```python
is_logged_in = False
if not is_logged_in:
    print("Please log in first")
```

The logical unary operator `not` completely reverses the Boolean value of the expression following it. Since `is_logged_in` is `False`, the expression not `is_logged_in` evaluates directly to `Tru`e. Because the resulting evaluation state is true, the indented branch executes perfectly, printing: `Please log in first`.

### 🧠 What's happening behind the scenes:
When evaluating bare Boolean flags or using logical operators like `not`, CPython completely optimizes the bytecode instructions away from standard binary comparisons (`COMPARE_OP`), relying instead on specialized, high-speed stack evaluation shortcuts.

Let's dissect the disassembled bytecode for both variations to see this compiler optimization in action:

## Variation A: Direct Boolean Check (`if is_logged_in:`)
```text
1             0 LOAD_NAME                0 (is_logged_in)
              2 POP_JUMP_IF_FALSE        6 (to 16)

2             4 LOAD_NAME                1 (print)
              6 LOAD_CONST               0 ('Welcome back!')
              8 CALL                     1
              14 POP_TOP
        >>   16 LOAD_CONST               1 (None)
             18 RETURN_VALUE
```

Optimized Branching: Notice that there is no comparison instruction (`COMPARE_OP`) generated here. CPython loads the variable reference directly onto the evaluation stack via `LOAD_NAME` and immediately runs `POP_JUMP_IF_FALSE`. The virtual machine evaluates the raw truth value of the object sitting on the stack. If it is `True`, it falls straight through to the print block; if it is `False`, it modifies the frame instruction registry pointer to jump straight to offset `16`.

## Variation B: The Inverted Logic Check (`if not is_logged_in:`)
```text
1             0 LOAD_NAME                0 (is_logged_in)
              2 POP_JUMP_IF_TRUE         6 (to 16)

2             4 LOAD_NAME                1 (print)
              6 LOAD_CONST               0 ('Please log in first')
              8 CALL                     1
             14 POP_TOP
        >>   16 LOAD_CONST               1 (None)
             18 RETURN_VALUE
```

The Compiler Shortcut: Look closely at instruction offset `2`. Instead of wasting cycles generating an explicit logical negation bytecode instruction (such as `UNARY_NOT`) followed by a secondary jump instruction, the CPython compiler optimizes the entire sequence into a single smart instruction: `POP_JUMP_IF_TRUE`.

Instead of explicitly calculating the inverse of the boolean and testing if that intermediate result is false, the VM reads the raw `False` state of `is_logged_in` directly from the stack. Because the state is `False`, `POP_JUMP_IF_TRUE` elects not to take the jump, allowing execution to naturally step straight into the indented print block located directly below it!
