> ⚠️ **Under Development:** This chapter is currently being written and compiled. Code snippets, explanations, and under-the-hood deep dives are subject to active updates.

© 2026 David Vael | Licensed under CC-BY 4.0
### The `if` Statement in Python
The `if` statement is one of the most fundamental building blocks of programming in Python. It allows your program to make decisions and execute specific code blocks only when certain conditions are met a concept known as **conditional execution** or **control flow**. Without conditional statements, software would be entirely linear and rigid, running the exact same way every time without any ability to respond to varying inputs or states.

### 📋 Basic Syntax
The foundational structural layout of an `if` statement relies entirely on Python's unique, whitespace-driven block-scoping rules:
```python
if condition:
    # Code block to execute
    # This runs only if the condition evaluates to True or Truthy
```

### Key Components:
- **The if Keyword:** Initiates the conditional evaluation check sequence inside the execution scope.
- **The Condition:** An expression that is evaluated down to a Boolean value (`True` or `False`). If the target expression yields a non-Boolean object (e.g., a list, string, or number), Python automatically evaluates its implicit truthiness or falsiness using its internal `PyObject_IsTrue()` C-level logic slots.
- **The Colon (`:`):** A mandatory character at the termination of the conditional clause line. It serves as a structural token signaling to the compiler that an indented code block follows immediately.
- **Indentation:** The lines of code intended to execute within the true branch path must be uniformly indented (the universal Python standard is 4 spaces). Unlike languages like C++, Java, or JavaScript that utilize explicit curly braces `{}` to isolate local scopes, Python enforces structural semantic layout directly via whitespace constraints.

### ⚙️ How It Works
When the CPython runtime engine encounters an `if` statement, it executes a clean, three step evaluation and branching routine.
```text
[ Evaluate Condition Expression ]
                       |
             Is it Truthy / True?
                    /     \
                (Yes)     (No)
                 /           \
     [ Run Indented Block ]   |
                 \           /
       [ Continue Program Execution ]
```
1. **Evaluate the Condition Expression:** The virtual machine engine processes the expression to determine whether it safely maps down to a `True` or `False` state.
2. **Execute Conditionally:**
    - **The True Path:** If the condition evaluates to `True`, the execution pointer enters the indented code block space and runs the statements inside sequentially.
    - **The False Path:** If the condition evaluates to `False`, the virtual machine alters its internal instruction registry pointer to hop over the indented code block entirely.
3. **Resume Linear Execution:** Once the conditional block has either successfully finished running or been bypassed by the engine, Python resumes executing the remaining unindented code lines sequentially down the file.

### 📋 Code Implementation Examples

## Example 1: Basic Condition with Comparison
```python
age = 18
if age >= 18:
    print("You are eligible to vote")
```
**Step-By-Step Breakdown:**
1. **Variable Assignment:** `age = 18` creates the identifier reference name `age` and binds it to a `PyLongObject` integer value of `18` in the local namespace.
2. **Condition Check:** `age >= 18` invokes the greater-than-or-equal-to comparison operator to evaluate the value bound to `age` against the literal `18`.
3. **Evaluation:** Since $18 \ge 18$ is mathematically true, the expression yields a pointer reference to the global Boolean singleton `True`.
4. **Execution:** The condition passes, triggering the indented block. The `print()` function executes and displays: `You are eligible to vote`.

## What if `age` was 17?
```python
age = 17
if age >= 18:
print("You are eligible to vote")
```
Now, the comparison expression evaluates $17 \ge 18$, which yields `False`. Because the condition fails, the virtual machine shifts its internal instruction registry pointer to hop directly over the indented print block. The program simply moves on to the next unindented line, and nothing is printed to `stdout`.

### 🧠 What's happening behind the scenes:
Let’s lift up the hood and look at the exact CPython bytecode generated for this basic `if` statement block. When Python compiles this script, it uses conditional jump instructions to handle the execution flow routing.

If we pass this code through Python’s internal `dis` (disassembler) module, the bytecode layout resolves like this:

```text
1             0 LOAD_NAME                0 (age)
              2 LOAD_CONST               0 (18)
              4 COMPARE_OP              74 (>=)
              10 POP_JUMP_IF_FALSE        6 (to 24)

2             12 LOAD_NAME                1 (print)
              14 LOAD_CONST               1 ('You are eligible to vote')
              16 CALL                     1
              22 POP_TOP
         >>   24 LOAD_CONST               2 (None)
              26 RETURN_VALUE
```

**The Evaluation Flow Control Steps:**
1. **`LOAD_NAME` & `LOAD_CONST`:** CPython pushes the value pointer stored in the variable `age` onto the evaluation stack, followed quickly by the constant literal value `18`.
2. **COMPARE_OP:** The virtual machine pops both values off the stack, executes the binary comparison (`>=`) at the C layer, and pushes the resulting boolean singleton (`True` or `False`) right back onto the head of the evaluation stack.
3. **`POP_JUMP_IF_FALSE`:** This is where the core magic of control flow routing happens. This instruction pops the Boolean result off the top of the stack and inspects its state:
    - **The `True` Path:** If the value is `True`, the instruction does nothing, and the virtual machine naturally slips down to the very next sequence line of bytecode (`LOAD_NAME` for the print function at offset 12).
    - **The `False` Path:** If the value is `False`, the instruction updates the VM's internal instruction pointer registry and completely jumps the execution track down to offset `24` (`LOAD_CONST None`). By forcing a branch jump directly to offset 24, it entirely skips the sequential instructions responsible for loading, setting up, and invoking the `CALL` stack for the `print()` function!
   

### Example 2: Using a Boolean Variable
```python
is_logged_in = True
if is_logged_in:
    print("Welcome back!")
```

## Step-By-Step Breakdown:
1. **Boolean Evaluation:** The identifier name `is_logged_in` is directly bound to the global Boolean singleton `True`. Because it is already a Boolean object, no evaluation modifier or comparison operator is required.
2. **Direct Evaluation:** Writing `if is_logged_in:` is functionally identical to writing `if is_logged_in == True:`, but the shorter form bypasses raw comparison overhead and is the highly preferred, idiomatic Pythonic approach.
3. **Result:** Since the variable directly holds a true value, the condition evaluates successfully and prints: `Welcome back!`.

## Alternative: Checking for `False` states with Logical Inversion
```python
is_logged_in = False
if not is_logged_in:
    print("Please log in first")
```

The logical unary operator `not` completely reverses the Boolean value of the expression following it. Since `is_logged_in` is `False`, the expression not `is_logged_in` evaluates directly to `Tru`e. Because the resulting evaluation state is true, the indented branch executes perfectly, printing: `Please log in first`.

### 🧠 What's happening behind the scenes:
When evaluating bare Boolean flags or using logical operators like `not`, CPython completely optimizes the bytecode instructions away from standard binary comparisons (`COMPARE_OP`), relying instead on specialized, high-speed stack evaluation shortcuts.

Let's dissect the disassembled bytecode for both variations to see this compiler optimization in action:

## Variation A: Direct Boolean Check (`if is_logged_in:`)
```text
1             0 LOAD_NAME                0 (is_logged_in)
              2 POP_JUMP_IF_FALSE        6 (to 16)

2             4 LOAD_NAME                1 (print)
              6 LOAD_CONST               0 ('Welcome back!')
              8 CALL                     1
              14 POP_TOP
        >>   16 LOAD_CONST               1 (None)
             18 RETURN_VALUE
```

Optimized Branching: Notice that there is no comparison instruction (`COMPARE_OP`) generated here. CPython loads the variable reference directly onto the evaluation stack via `LOAD_NAME` and immediately runs `POP_JUMP_IF_FALSE`. The virtual machine evaluates the raw truth value of the object sitting on the stack. If it is `True`, it falls straight through to the print block; if it is `False`, it modifies the frame instruction registry pointer to jump straight to offset `16`.

## Variation B: The Inverted Logic Check (`if not is_logged_in:`)
```text
1             0 LOAD_NAME                0 (is_logged_in)
              2 POP_JUMP_IF_TRUE         6 (to 16)

2             4 LOAD_NAME                1 (print)
              6 LOAD_CONST               0 ('Please log in first')
              8 CALL                     1
             14 POP_TOP
        >>   16 LOAD_CONST               1 (None)
             18 RETURN_VALUE
```

**The Compiler Shortcut:** Look closely at instruction offset `2`. Instead of wasting cycles generating an explicit logical negation bytecode instruction (such as `UNARY_NOT`) followed by a secondary jump instruction, the CPython compiler optimizes the entire sequence into a single smart instruction: `POP_JUMP_IF_TRUE`.

Instead of explicitly calculating the inverse of the boolean and testing if that intermediate result is false, the VM reads the raw `False` state of `is_logged_in` directly from the stack. Because the state is `False`, `POP_JUMP_IF_TRUE` elects not to take the jump, allowing execution to naturally step straight into the indented print block located directly below it!

### Example 3: Number Comparison (Introducing the else Fallback)
```python
temperature = 30
if temperature > 25:
    print("It's hot outside")
else:
    print("It's cool outside")
```

**Terminal Output:**
```text
It's hot outside
```
## Step-by-Step Breakdown:
1. **Condition Evaluation:** The condition `temperature > 25` compares the value stored in the variable `temperature (30)` against the literal integer `25`.
2. **True Path Execution:** Since $30 > 25$ is mathematically true, the expression yields the global Boolean singleton `True`. The `if` block triggers immediately, printing `"It's hot outside"`.
3. **Skipping the Alternative:** Because the primary condition succeeded, the engine completely bypasses the `else` block fallback, preventing its internal code from executing.

### 🧠 What's happening behind the scenes:
When an `else` branch is added to a conditional structure, the CPython compiler must generate a way to exit the entire logical block cleanly after the `if` block finishes running. It accomplishes this by injecting an unconditional jump instruction (`JUMP_FORWARD` or `JUMP_BACKWARD`) right at the terminal tail of the true `if` block code execution array.

Let’s dissect the disassembled bytecode for this `if-else` dual-branch layout:
```text
1            0 LOAD_NAME                 0 (temperature)
             2 LOAD_CONST                0 (25)
             4 COMPARE_OP                68 (>)
             10 POP_JUMP_IF_FALSE        8 (to 28)

2            12 LOAD_NAME                1 (print)
             14 LOAD_CONST               1 ("It's hot outside")
             16 CALL                     1
             22 POP_TOP
             24 JUMP_FORWARD             7 (to 40)

4       >>   28 LOAD_NAME                1 (print)
             30 LOAD_CONST               2 ("It's cool outside")
             32 CALL                     1
             38 POP_TOP
        >>   40 LOAD_CONST               3 (None)
             42 RETURN_VALUE
```

## The Dual-Branch Control Flow Steps:
1. **The Conditional Split (`POP_JUMP_IF_FALSE`):** CPython loads `temperature` and `25`, runs the comparison instruction, and evaluates the stack state. If the condition evaluates to `False`, the instruction pointer jumps explicitly to offset `28`. This skips the hot-weather print block entirely and lands execution directly at the threshold of the `else` block logic.
2. **The Success Escape Hatch (`JUMP_FORWARD`):** If the comparison is `True`, execution falls through linearly into the first print routine (offsets `12` to `22`). However, notice what happens at offset `24` right after the print call clears the stack: CPython executes a `JUMP_FORWARD` directly to offset `40`.
- **Preventing Operational Collision:** Without that `JUMP_FORWARD` instruction, the CPU would blindly continue executing the next sequential lines of compiled bytecode in memory, meaning it would run the `if` block code and then immediately crash straight through into executing the alternative `else` block code right after it! The compiler injects `JUMP_FORWARD` as an essential safety gate to skip past the alternative branch once a valid path has been fully satisfied.

 ### Example 4: User Authentication (String Comparison and Dynamic Input)
 ```python
password = input("Enter password: ")
if password == "secret123":
    print("Access granted")
else:
    print("Access denied")
```

## Operational Explanation:
1. **Dynamic Input Evaluation:** The program pauses execution at runtime to accept an arbitrary string from the user via the built in `input()` function, binding the resulting string object reference to the identifier `password`.
2. **String Matching Check:** The `==` operator verifies if the characters within the `password` variable match the hardcoded character sequence `"secret123"`.
3. **Branch Routing:** If the input string matches perfectly, the condition evaluates to `True` and access is granted. Any other input text (even a case mismatch) causes the structural comparison to fail (`False`), routing execution straight into the fallback `else` block to deny access.

### 🧠 What's happening behind the scenes:
When comparing strings inside an `if` condition, CPython skips standard primitive mathematical evaluations and leverages highly optimized string equality routines at the internal C level.
Let’s inspect the generated bytecode for this authentication routing framework:
```text
1             0 LOAD_NAME                0 (input)
              2 LOAD_CONST               0 ('Enter password: ')
              4 CALL                     1
              12 STORE_NAME              1 (password)

  2          14 LOAD_NAME                1 (password)
             16 LOAD_CONST               1 ('secret123')
             18 COMPARE_OP              72 (==)
             24 POP_JUMP_IF_FALSE        8 (to 42)

  3          26 LOAD_NAME                2 (print)
             28 LOAD_CONST               2 ('Access granted')
             30 CALL                     1
             36 POP_TOP
             38 JUMP_FORWARD             7 (to 54)

  5     >>   42 LOAD_NAME                2 (print)
             44 LOAD_CONST               3 ('Access denied')
             46 CALL                     1
             52 POP_TOP
        >>   54 LOAD_CONST               4 (None)
             56 RETURN_VALUE
```

## The Evaluation Architecture:
1. **String Evaluation Pointer Check (`COMPARE_OP`):** At instruction offset `18`, CPython pops the user defined `password` variable and the constant string literal `'secret123'` off the top of the evaluation stack to run the equality check. Under the hood, the virtual machine invokes CPython's internal C API function `unicode_eq()`.
2. **The C-Layer Short-Circuit Optimization:** Before iterating through individual characters in the string array, the `unicode_eq()` function executes two high speed structural shortcut checks to minimize execution overhead:
    - **Identity Verification:** It first checks if the two string operands share the exact same memory pointer address. If they are the exact same object in memory, it instantly returns `True` without scanning a single character.
    - **Length Verification:** If the string memory pointers differ, it compares their internal size variables. If string length $A \neq$ string length $B$, CPython immediately bypasses character-by-character comparison entirely and returns `False` instantly.
3. **The Control Flow Skip:** If either shortcut fails or a character mismatch is caught during the fallback array loop, `COMPARE_OP` pushes a `False` token onto the evaluation stack. The subsequent `POP_JUMP_IF_FALSE` instruction instantly reads that state and jumps execution directly to offset `42`, completely shielding the secure `'Access granted'` bytecode instructions from being touched by the processor.

### Multiple Statements in Each Block
Both the `if` and `else` blocks are not limited to single, isolated actions; they can house an arbitrary number of sequential lines of code. Python maintains the absolute integrity of these execution streams purely through consistent indentation tracking.
```python
balance = 50
withdrawal = 100

if withdrawal <= balance:
    balance -= withdrawal
    print("Withdrawal successful")
    print(f"New balance: {balance}")
else:
    print("Insufficient funds")
    print(f"Current balance: {balance}")
    print("Please deposit more money")
```

## Terminal Output
```text
Insufficient funds
Current balance: 50
Please deposit more money
```

## Operational Explanation:
1. **The Condition Check:** The comparison condition `withdrawal <= balance` checks whether $100 \le 50$, which instantly evaluates down to a `False` boolean state.
2. **Block Execution Flow:** Because the condition fails, CPython shifts its active instruction track past the entire true branch code suite. It immediately executes all three statements grouped within the indented `else` block sequentially, while completely shielding all three statements inside the true `if` block from execution.

## 🧠 What's happening behind the scenes:
When a logical branch block contains multiple lines of code, the CPython compiler treats the collection of indented statement lines as a single, contiguous sequential execution block. The offset address targeted by conditional jumps routes the virtual machine's instruction pointer past the entire multi-line block layout in a single cycle, rather than resolving jumps line-by-line.

Let's dissect the generated bytecode layout for these multi-statement suites to observe how indentation maps to hard hardware offsets:

```text
4            0 LOAD_NAME                0 (withdrawal)
              2 LOAD_NAME                1 (balance)
              4 COMPARE_OP              70 (<=)
             10 POP_JUMP_IF_FALSE       14 (to 40)

  5          12 LOAD_NAME                1 (balance)
             14 LOAD_NAME                0 (withdrawal)
             16 BINARY_OP                23 (-=)
             20 STORE_NAME               1 (balance)

  6          22 LOAD_NAME                2 (print)
             24 LOAD_CONST               0 ('Withdrawal successful')
             26 CALL                     1
             32 POP_TOP

  7          34 ... [print call for New Balance] ...
             38 JUMP_FORWARD            21 (to 82)

  9     >>   40 LOAD_NAME                2 (print)
             42 LOAD_CONST               2 ('Insufficient funds')
             44 CALL                     1
             50 POP_TOP

 10          52 LOAD_NAME                2 (print)
             54 ... [String Formatting & Print Call for Current Balance] ...
             64 POP_TOP

 11          66 LOAD_NAME                2 (print)
             68 LOAD_CONST               4 ('Please deposit more money')
             70 CALL                     1
             76 POP_TOP
        >>   82 LOAD_CONST               5 (None)
             84 RETURN_VALUE
```

## The Multi-Line Routing Mechanics:
1. **The Block Leap (`POP_JUMP_IF_FALSE`):** When `withdrawal <= balance` returns `False`, the instruction at offset `10` reads the stack state and forces the virtual machine's instruction pointer to hop straight to offset `40`. This single, high-speed structural jump bypasses the local variable mutation (`-=`) and both subsequent `print` function setups (offsets `12` through `38`) in a single, macro-level maneuver.
2. **Linear Drop-Through Optimization:** Once execution lands at offset `40`, the frame execution track falls straight through every sequential bytecode instruction mapped to source lines 9, 10, and 11 naturally. CPython doesn't need to waste cycles executing extra validation checks or monitoring boundaries to stay inside the `else` block; it simply processes instructions serially until the execution frame completes.
3. **Unified Structural Boundaries:** This architectural layout proves that Python's syntactic indentation rules are translated directly into absolute memory offset index numbers during compilation. An entire code block is functionally bounded by a single conditional jump instruction at its entry point, and an unconditional escape hatch (`JUMP_FORWARD`) at its terminal execution tail.

### 🧭 Strategic Application: When to Use `if-else`
Architecting decision making logic in high-performance production code requires choosing the most precise control flow structure for the problem space. An `if-else` statement is specifically engineered for structural bifurcations where execution must diverge down exactly one of two available, mutually exclusive paths.
You should implement an `if-else` pattern when your application logic meets the following operational parameters:
   - **A Mandatory Default Action is Required:** If the primary conditional expression evaluates to `False`, your application shouldn't simply sit idle or drop into the next linear step it must execute an alternative block of code to cleanly handle, normalize, or log the fallback state.
   - **The Logic is Strictly Binary:** The dataset, condition state, or truth vector resolves cleanly to exactly two mutually exclusive outcomes: $A$ or $B$ (e.g., `Yes`/`No`, `Pass`/`Fail`, `Valid`/`Invalid`, `Authorized`/`Unauthorized`).
   - **Mitigating Silent Failures:** Without a terminal `else` block, an unhandled `False` state causes the runtime engine to slip quietly past the conditional structure without modifying states or alerting the application context. An `else` wrapper acts as a foundational defensive programming mechanism, providing immediate architectural feedback or alternative behavior routing instead of letting anomalies fail silently.

### 🧠 What's happening behind the scenes:
At the compiler level, Python optimizes binary logic because it can explicitly rely on two terminal offset jump targets. When you provide an explicit `else` block rather than just an isolated `if` statement, the CPython compiler modifies how it maps out the local execution scope's structural optimization.

Consider the structural layout contrast in generated bytecode between an **Isolated** `if` and a **Balanced** `if-else`:

## Pattern A: Isolated `if` (No Fallback Branch)
```text
  1           0 LOAD_NAME                0 (is_valid)
              2 POP_JUMP_IF_FALSE        4 (to 12)
              
  2           4 LOAD_NAME                1 (print)
              6 LOAD_CONST               0 ('Valid!')
              8 CALL                     1
             14 POP_TOP
             
        >>   12 LOAD_CONST               1 (None)
```
**Mechanics:** If `is_valid` evaluates to `False`, the virtual machine jumps directly to the end of the script frame context at offset `12`. There are no alternative operational paths to resolve, load, or evaluate; the runtime environment immediately cleans up the evaluation stack frame.

## Pattern B: Balanced `if-else` (Defensive Logic)
```text
  1           0 LOAD_NAME                0 (is_valid)
              2 POP_JUMP_IF_FALSE        8 (to 18)
              
  2           4 LOAD_NAME                1 (print)
              6 LOAD_CONST               0 ('Valid!')
              8 CALL                     1
             14 POP_TOP
             16 JUMP_FORWARD             7 (to 28)
             
  4     >>   18 LOAD_NAME                1 (print)
             20 LOAD_CONST               1 ('Invalid state caught!')
             22 CALL                     1
             26 POP_TOP
             
        >>   28 LOAD_CONST               2 (None)
```
## The Structural Safety Net:
Notice that adding an `else` branch structurally transforms the fallback target mapping of the instruction at offset `2`. Instead of dropping the execution track cleanly into an empty namespace cleanup tail, `POP_JUMP_IF_FALSE` explicitly routes control straight to offset `18`.

This forces the virtual machine frame to actively reconstruct the evaluation stack using the instructions bound exclusively to the fallback block. CPython leverages this clear segmentation to avoid state ambiguity ensuring that the underlying hardware execution pipeline registers exactly one clear structural branch modification per block, maximizing the branch predictor's efficiency on the host CPU.

